{
  "entityType" : "DEVICE",
  "entity" : {
    "additionalInfo" : {
      "gateway" : false,
      "overwriteActivityTime" : false,
      "description" : ""
    },
    "customerId" : {
      "entityType" : "CUSTOMER",
      "id" : "13814000-1dd2-11b2-8080-808080808080"
    },
    "deviceData" : {
      "configuration" : {
        "type" : "DEFAULT"
      },
      "transportConfiguration" : {
        "type" : "DEFAULT"
      }
    },
    "deviceProfileId" : {
      "entityType" : "DEVICE_PROFILE",
      "id" : "f72527d0-afee-11f0-80dc-a13212beee54"
    },
    "externalId" : null,
    "firmwareId" : {
      "entityType" : "OTA_PACKAGE",
      "id" : "9e7ef3d0-afef-11f0-80dc-a13212beee54"
    },
    "id" : {
      "entityType" : "DEVICE",
      "id" : "1337bd70-afef-11f0-80dc-a13212beee54"
    },
    "label" : "",
    "name" : "testDev",
    "softwareId" : null,
    "type" : "otaTest"
  },
  "credentials" : {
    "credentialsId" : "16TvMyS9pSyf2CWfMwFt",
    "credentialsType" : "ACCESS_TOKEN",
    "credentialsValue" : null
  },
  "attributes" : {
    "SERVER_SCOPE" : [ {
      "booleanValue" : false,
      "doubleValue" : null,
      "jsonValue" : null,
      "key" : "active",
      "lastUpdateTs" : 1761210180344,
      "longValue" : null,
      "strValue" : null
    } ],
    "SHARED_SCOPE" : [ ]
  },
  "calculatedFields" : [ ]
}